models/__init__.py
models/base_classification_model.py
models/base_model.py
models/base_regression_model.py
models/classification/__init__.py
models/classification/gb.py
models/classification/rf.py
models/classification/xgb.py
models/regression/__init__.py
hyperband_multithreading-0.0.1.dist-info/METADATA
hyperband_multithreading-0.0.1.dist-info/WHEEL
hyperband_multithreading-0.0.1.dist-info/top_level.txt
hyperband_multithreading-0.0.1.dist-info/RECORD
