Metadata-Version: 2.1
Name: hyperband-multithreading
Version: 0.0.1
Summary: Hyperband-multithreading
Home-page: UNKNOWN
Author: Mikhail Bogomazov
Author-email: <youremail@email.com>
License: UNKNOWN
Keywords: python,data science,hyperopt,hyperband
Platform: UNKNOWN
Classifier: Development Status :: 3 - Alpha
Classifier: Intended Audience :: Education
Classifier: Programming Language :: Python :: 2
Classifier: Programming Language :: Python :: 3
Classifier: Operating System :: MacOS :: MacOS X
Classifier: Operating System :: Microsoft :: Windows
Requires-Dist: hyperopt (==0.2.5)
Requires-Dist: ipython (==7.30.1)
Requires-Dist: keras (==2.7.0)
Requires-Dist: numpy (==1.19.2)
Requires-Dist: pandas (==1.1.3)
Requires-Dist: scikit-learn (==1.0.1)
Requires-Dist: xgboost (==1.5.1)
